pylon/__init__.py
pylon/analyzer.py
pylon/calc.py
pylon/main.py
pylon/misc.py
pylon/visualizer.py
pylon/pbp/__init__.py
pylon/pbp/functions.py
pylon/util/__init__.py
pylon/util/urls.py
nfl_pylon-0.0.2.dist-info/LICENSE
nfl_pylon-0.0.2.dist-info/METADATA
nfl_pylon-0.0.2.dist-info/WHEEL
nfl_pylon-0.0.2.dist-info/top_level.txt
nfl_pylon-0.0.2.dist-info/RECORD
